panorai/__init__.py
panorai/__init__.pyi
panorai/path_config.py
panorai/path_config.pyi
panorai/blenders/__init__.py
panorai/blenders/__init__.pyi
panorai/blenders/average.py
panorai/blenders/average.pyi
panorai/blenders/base_blenders.py
panorai/blenders/base_blenders.pyi
panorai/blenders/bundle_adjustment.py
panorai/blenders/bundle_adjustment.pyi
panorai/blenders/closest.py
panorai/blenders/closest.pyi
panorai/blenders/feathering.py
panorai/blenders/feathering.pyi
panorai/blenders/gaussian.py
panorai/blenders/gaussian.pyi
panorai/blenders/huber.py
panorai/blenders/huber.pyi
panorai/blenders/huber_no_confidence.py
panorai/blenders/huber_no_confidence.pyi
panorai/blenders/huber_spatial_blender.py
panorai/blenders/huber_spatial_blender.pyi
panorai/blenders/overlap_counter.py
panorai/blenders/overlap_counter.pyi
panorai/blenders/overlap_std_blender.py
panorai/blenders/overlap_std_blender.pyi
panorai/blenders/registry.py
panorai/blenders/registry.pyi
panorai/blenders/std_feathering.py
panorai/blenders/std_feathering.pyi
panorai/config/__init__.py
panorai/config/__init__.pyi
panorai/config/config_manager.py
panorai/config/config_manager.pyi
panorai/config/registry.py
panorai/config/registry.pyi
panorai/data/__init__.py
panorai/data/__init__.pyi
panorai/data/array_data.py
panorai/data/array_data.pyi
panorai/data/equirectangular_image.py
panorai/data/equirectangular_image.pyi
panorai/data/factory.py
panorai/data/factory.pyi
panorai/data/gnomonic_image.py
panorai/data/gnomonic_image.pyi
panorai/data/gnomonic_imageset.py
panorai/data/gnomonic_imageset.pyi
panorai/data/multi_data.py
panorai/data/multi_data.pyi
panorai/data/multi_handler.py
panorai/data/multi_handler.pyi
panorai/data/spherical_data.py
panorai/data/spherical_data.pyi
panorai/data/utils/__init__.py
panorai/data/utils/__init__.pyi
panorai/data/utils/misc.py
panorai/data/utils/misc.pyi
panorai/data/utils/shape_manager.py
panorai/data/utils/shape_manager.pyi
panorai/depth/__init__.py
panorai/depth/registry.py
panorai-3.0.19.dist-info/licenses/LICENSE
panorai-3.0.19.dist-info/METADATA
panorai-3.0.19.dist-info/WHEEL
panorai-3.0.19.dist-info/top_level.txt
panorai-3.0.19.dist-info/RECORD
