Metadata-Version: 2.4
Name: panorai
Version: 3.0.19
Summary: Panoramic image projection and blending using Gnomonic and other spherical projections.
Home-page: https://github.com/RobinsonGarcia/PanorAi
Author: Robinson Luiz Souza Garcia
Author-email: rlsgarcia@icloud.com
License: MIT
Project-URL: Bug Tracker, https://github.com/RobinsonGarcia/PanorAi/issues
Project-URL: Source Code, https://github.com/RobinsonGarcia/PanorAi
Project-URL: Documentation, https://github.com/RobinsonGarcia/PanorAi/wiki
Keywords: panorama,projection,gnomonic,spherical images,3D reconstruction,computer vision
Classifier: Development Status :: 3 - Alpha
Classifier: Intended Audience :: Developers
Classifier: Topic :: Scientific/Engineering :: Image Processing
Classifier: License :: OSI Approved :: MIT License
Classifier: Operating System :: OS Independent
Classifier: Programming Language :: Python :: 3
Classifier: Programming Language :: Python :: 3.7
Classifier: Programming Language :: Python :: 3.8
Classifier: Programming Language :: Python :: 3.9
Classifier: Programming Language :: Python :: 3.10
Classifier: Programming Language :: Python :: 3.11
Requires-Python: >=3.7
License-File: LICENSE
Requires-Dist: numpy>=2.3.0
Requires-Dist: scipy
Requires-Dist: joblib
Requires-Dist: torch
Requires-Dist: scikit-image
Requires-Dist: opencv-python-headless
Requires-Dist: pydantic>=2.0.0
Requires-Dist: pyyaml
Requires-Dist: open3d
Provides-Extra: dev
Requires-Dist: pytest; extra == "dev"
Requires-Dist: pytest-cov; extra == "dev"
Requires-Dist: flake8; extra == "dev"
Requires-Dist: black; extra == "dev"
Requires-Dist: mypy; extra == "dev"
Provides-Extra: docs
Requires-Dist: sphinx; extra == "docs"
Requires-Dist: sphinx-rtd-theme; extra == "docs"
Provides-Extra: depth
Requires-Dist: DateTime; extra == "depth"
Requires-Dist: Pillow; extra == "depth"
Requires-Dist: PyYAML; extra == "depth"
Requires-Dist: accelerate; extra == "depth"
Requires-Dist: albumentations; extra == "depth"
Requires-Dist: einops; extra == "depth"
Requires-Dist: gradio; extra == "depth"
Requires-Dist: gradio_imageslider; extra == "depth"
Requires-Dist: h5py; extra == "depth"
Requires-Dist: huggingface-hub[torch]>=0.22; extra == "depth"
Requires-Dist: imagecorruptions; extra == "depth"
Requires-Dist: imgaug; extra == "depth"
Requires-Dist: iopath; extra == "depth"
Requires-Dist: joblib; extra == "depth"
Requires-Dist: matplotlib; extra == "depth"
Requires-Dist: mmcv; extra == "depth"
Requires-Dist: mmengine; extra == "depth"
Requires-Dist: numpy>=1.26; extra == "depth"
Requires-Dist: open3d; extra == "depth"
Requires-Dist: opencv-python; extra == "depth"
Requires-Dist: plyfile; extra == "depth"
Requires-Dist: pydantic; extra == "depth"
Requires-Dist: pyglet<2; extra == "depth"
Requires-Dist: roma; extra == "depth"
Requires-Dist: scikit-image; extra == "depth"
Requires-Dist: scikit-learn; extra == "depth"
Requires-Dist: scipy; extra == "depth"
Requires-Dist: spherical-projections==0.1.2b0; extra == "depth"
Requires-Dist: tensorboard; extra == "depth"
Requires-Dist: tensorboardX; extra == "depth"
Requires-Dist: torch; extra == "depth"
Requires-Dist: torchvision; extra == "depth"
Requires-Dist: tqdm; extra == "depth"
Requires-Dist: trimesh; extra == "depth"
Requires-Dist: wandb; extra == "depth"
Requires-Dist: xformers; extra == "depth"
Dynamic: author
Dynamic: author-email
Dynamic: classifier
Dynamic: description
Dynamic: description-content-type
Dynamic: home-page
Dynamic: keywords
Dynamic: license
Dynamic: license-file
Dynamic: project-url
Dynamic: provides-extra
Dynamic: requires-dist
Dynamic: requires-python
Dynamic: summary
